rbot-0.3.5.dist-info/METADATA
rbot-0.3.5.dist-info/WHEEL
rbot-0.3.5.dist-info/license_files/LICENSE.txt
rbot-0.3.5.dist-info/license_files/LICENSE.txt
rbot/__init__.py
rbot/rbot.pyd
rbot-0.3.5.dist-info/RECORD
