Metadata-Version: 2.1
Name: rbot
Version: 0.3.5
Classifier: Intended Audience :: Developers
Classifier: Programming Language :: Rust
Classifier: Programming Language :: Python :: Implementation :: CPython
Classifier: Programming Language :: Python :: Implementation :: PyPy
Classifier: License :: OSI Approved :: GNU Lesser General Public License v3 or later (LGPLv3+)
License-File: LICENSE.txt
License-File: LICENSE.txt
Summary: crypt trading framework, support back_test, dry_run and real_run
Author: @yasstake
Requires-Python: >=3.8
Project-URL: Documentation, https://github.com/yasstake/rusty-bot
Project-URL: Repository, https://github.com/yasstake/rbot
